sci_paper_rename/__init__.py
sci_paper_rename/__main__.py
sci_paper_rename/helper.py
sci_paper_rename-1.0.3.dist-info/licenses/LICENSE
sci_paper_rename-1.0.3.dist-info/METADATA
sci_paper_rename-1.0.3.dist-info/WHEEL
sci_paper_rename-1.0.3.dist-info/entry_points.txt
sci_paper_rename-1.0.3.dist-info/top_level.txt
sci_paper_rename-1.0.3.dist-info/RECORD
