Metadata-Version: 2.4
Name: sci-paper-rename
Version: 1.0.3
Summary: A tool that automatically renames scientific paper PDF files based on their titles. It scans the PDF content to detect the paper’s title and uses it to generate a clean, meaningful filename.
Author-email: "Heverson B. Ribeiro" <heversonbr@gmail.com>
License: GNU Affero General Public License v3
Project-URL: Homepage, https://github.com/heversonbr/sci-paper-rename
Project-URL: Bug Tracker, https://github.com/heversonbr/sci-paper-rename/issues
Classifier: Programming Language :: Python :: 3
Classifier: Programming Language :: Python :: 3.11
Classifier: License :: OSI Approved :: GNU Affero General Public License v3
Classifier: Operating System :: OS Independent
Requires-Python: <3.12.0,>=3.11.6
License-File: LICENSE
Requires-Dist: PyMuPDF==1.26.0
Dynamic: license-file
